setup.py
./cyassimp/cyassimpwrapper.cpp
./cyassimp/cyassimpwrapper.pyx
./cyassimp/cpp/assimpwrapper.cpp
cyassimp/__init__.py
cyassimp/cyassimpwrapper.cpp
cyassimp/cyassimpwrapper.pyx
cyassimp.egg-info/PKG-INFO
cyassimp.egg-info/SOURCES.txt
cyassimp.egg-info/dependency_links.txt
cyassimp.egg-info/requires.txt
cyassimp.egg-info/top_level.txt
cyassimp/cpp/assimpwrapper.cpp
cyassimp/cpp/assimpwrapper.h