Metadata-Version: 1.1
Name: cyassimp
Version: 0.1.3
Summary: Fast Cython bindings for The Open Assimp Import Library
Home-page: UNKNOWN
Author: James Booth
Author-email: james.booth08@imperial.ac.uk
License: UNKNOWN
Platform: UNKNOWN
Classifier: Development Status :: 3 - Alpha
Classifier: Intended Audience :: Developers
Classifier: Intended Audience :: Science/Research
Classifier: License :: OSI Approved :: BSD License
Classifier: Operating System :: OS Independent
Classifier: Programming Language :: C++
Classifier: Programming Language :: Cython
Classifier: Programming Language :: Python :: 2
Classifier: Programming Language :: Python :: 2.7
